setup.py
padnas/__init__.py
padnas/cli.py
padnas.egg-info/PKG-INFO
padnas.egg-info/SOURCES.txt
padnas.egg-info/dependency_links.txt
padnas.egg-info/entry_points.txt
padnas.egg-info/top_level.txt